xzitaao/__init__.py
xzitaao-0.0.5.dist-info/LICENSE
xzitaao-0.0.5.dist-info/METADATA
xzitaao-0.0.5.dist-info/WHEEL
xzitaao-0.0.5.dist-info/top_level.txt
xzitaao-0.0.5.dist-info/RECORD
