Metadata-Version: 2.1
Name: xzitaao
Version: 0.0.5
Summary: Crawler for xzit aao
Home-page: https://github.com/Qualthera/xzitaao.git
Author: Qualthera
Author-email: qualthera@163.com
License: Apache License 2.0
Platform: all
Classifier: Programming Language :: Python :: 3
Classifier: Operating System :: OS Independent
Requires-Dist: beautifulsoup4 (==4.9.3)
Requires-Dist: bs4 (==0.0.1)
Requires-Dist: certifi (==2020.12.5)
Requires-Dist: chardet (==3.0.4)
Requires-Dist: cycler (==0.10.0)
Requires-Dist: idna (==2.10)
Requires-Dist: kiwisolver (==1.3.1)
Requires-Dist: lxml (==4.6.2)
Requires-Dist: numpy (==1.19.3)
Requires-Dist: Pillow (==8.0.1)
Requires-Dist: pyparsing (==2.4.7)
Requires-Dist: python-dateutil (==2.8.1)
Requires-Dist: requests (==2.25.0)
Requires-Dist: six (==1.15.0)
Requires-Dist: soupsieve (==2.1)
Requires-Dist: urllib3 (==1.26.2)
Requires-Dist: pytesseract (==0.3.6)
